[{"iob":1.764,"activity":0.006,"bolussnooze":1.212,"basaliob":0.416,"netbasalinsulin":-0.05,"hightempinsulin":0.85,"time":"2016-10-06T02:59:29.000Z"},{"iob":1.724,"activity":0.0079,"bolussnooze":1.114,"basaliob":0.402,"netbasalinsulin":0,"hightempinsulin":0.85,"time":"2016-10-06T03:04:29.000Z"},{"iob":1.675,"activity":0.0098,"bolussnooze":0.994,"basaliob":0.385,"netbasalinsulin":0,"hightempinsulin":0.85,"time":"2016-10-06T03:09:29.000Z"},{"iob":1.617,"activity":0.0116,"bolussnooze":0.854,"basaliob":0.363,"netbasalinsulin":0,"hightempinsulin":0.85,"time":"2016-10-06T03:14:29.000Z"},{"iob":1.552,"activity":0.0132,"bolussnooze":0.702,"basaliob":0.339,"netbasalinsulin":0,"hightempinsulin":0.85,"time":"2016-10-06T03:19:29.000Z"},{"iob":1.479,"activity":0.0146,"bolussnooze":0.565,"basaliob":0.313,"netbasalinsulin":0.05,"hightempinsulin":0.85,"time":"2016-10-06T03:24:29.000Z"},{"iob":1.4,"activity":0.0158,"bolussnooze":0.443,"basaliob":0.286,"netbasalinsulin":0.1,"hightempinsulin":0.85,"time":"2016-10-06T03:29:29.000Z"},{"iob":1.316,"activity":0.0167,"bolussnooze":0.336,"basaliob":0.259,"netbasalinsulin":0.15,"hightempinsulin":0.85,"time":"2016-10-06T03:34:29.000Z"},{"iob":1.228,"activity":0.0176,"bolussnooze":0.244,"basaliob":0.233,"netbasalinsulin":0.2,"hightempinsulin":0.85,"time":"2016-10-06T03:39:29.000Z"},{"iob":1.136,"activity":0.0184,"bolussnooze":0.166,"basaliob":0.209,"netbasalinsulin":0.25,"hightempinsulin":0.85,"time":"2016-10-06T03:44:29.000Z"},{"iob":1.04,"activity":0.0193,"bolussnooze":0.103,"basaliob":0.185,"netbasalinsulin":0.3,"hightempinsulin":0.85,"time":"2016-10-06T03:49:29.000Z"},{"iob":0.939,"activity":0.0201,"bolussnooze":0.055,"basaliob":0.162,"netbasalinsulin":0.35,"hightempinsulin":0.85,"time":"2016-10-06T03:54:29.000Z"},{"iob":0.843,"activity":0.0192,"bolussnooze":0.022,"basaliob":0.14,"netbasalinsulin":0.4,"hightempinsulin":0.85,"time":"2016-10-06T03:59:29.000Z"},{"iob":0.752,"activity":0.0182,"bolussnooze":0.004,"basaliob":0.119,"netbasalinsulin":0.45,"hightempinsulin":0.85,"time":"2016-10-06T04:04:29.000Z"},{"iob":0.666,"activity":0.0172,"bolussnooze":0,"basaliob":0.1,"netbasalinsulin":0.5,"hightempinsulin":0.85,"time":"2016-10-06T04:09:29.000Z"},{"iob":0.585,"activity":0.0162,"bolussnooze":0,"basaliob":0.082,"netbasalinsulin":0.55,"hightempinsulin":0.85,"time":"2016-10-06T04:14:29.000Z"},{"iob":0.509,"activity":0.0151,"bolussnooze":0,"basaliob":0.065,"netbasalinsulin":0.6,"hightempinsulin":0.85,"time":"2016-10-06T04:19:29.000Z"},{"iob":0.439,"activity":0.0141,"bolussnooze":0,"basaliob":0.05,"netbasalinsulin":0.65,"hightempinsulin":0.85,"time":"2016-10-06T04:24:29.000Z"},{"iob":0.374,"activity":0.013,"bolussnooze":0,"basaliob":0.037,"netbasalinsulin":0.7,"hightempinsulin":0.85,"time":"2016-10-06T04:29:29.000Z"},{"iob":0.315,"activity":0.0118,"bolussnooze":0,"basaliob":0.026,"netbasalinsulin":0.75,"hightempinsulin":0.85,"time":"2016-10-06T04:34:29.000Z"},{"iob":0.261,"activity":0.0107,"bolussnooze":0,"basaliob":0.017,"netbasalinsulin":0.75,"hightempinsulin":0.85,"time":"2016-10-06T04:39:29.000Z"},{"iob":0.213,"activity":0.0096,"bolussnooze":0,"basaliob":0.01,"netbasalinsulin":0.75,"hightempinsulin":0.85,"time":"2016-10-06T04:44:29.000Z"},{"iob":0.171,"activity":0.0084,"bolussnooze":0,"basaliob":0.005,"netbasalinsulin":0.7,"hightempinsulin":0.8,"time":"2016-10-06T04:49:29.000Z"},{"iob":0.135,"activity":0.0073,"bolussnooze":0,"basaliob":0.002,"netbasalinsulin":0.6,"hightempinsulin":0.7,"time":"2016-10-06T04:54:29.000Z"},{"iob":0.103,"activity":0.0063,"bolussnooze":0,"basaliob":0,"netbasalinsulin":0.5,"hightempinsulin":0.6,"time":"2016-10-06T04:59:29.000Z"},{"iob":0.076,"activity":0.0053,"bolussnooze":0,"basaliob":-0.001,"netbasalinsulin":0.35,"hightempinsulin":0.45,"time":"2016-10-06T05:04:29.000Z"},{"iob":0.054,"activity":0.0044,"bolussnooze":0,"basaliob":-0.001,"netbasalinsulin":0.25,"hightempinsulin":0.35,"time":"2016-10-06T05:09:29.000Z"},{"iob":0.036,"activity":0.0036,"bolussnooze":0,"basaliob":-0.001,"netbasalinsulin":0.1,"hightempinsulin":0.2,"time":"2016-10-06T05:14:29.000Z"},{"iob":0.022,"activity":0.0029,"bolussnooze":0,"basaliob":0,"netbasalinsulin":-0.05,"hightempinsulin":0.05,"time":"2016-10-06T05:19:29.000Z"},{"iob":0.011,"activity":0.0022,"bolussnooze":0,"basaliob":0,"netbasalinsulin":-0.1,"hightempinsulin":0,"time":"2016-10-06T05:24:29.000Z"},{"iob":0.004,"activity":0.0015,"bolussnooze":0,"basaliob":0,"netbasalinsulin":-0.05,"hightempinsulin":0,"time":"2016-10-06T05:29:29.000Z"},{"iob":0,"activity":0.0007,"bolussnooze":0,"basaliob":0,"netbasalinsulin":0,"hightempinsulin":0,"time":"2016-10-06T05:34:29.000Z"},{"iob":0,"activity":0,"bolussnooze":0,"basaliob":0,"netbasalinsulin":0,"hightempinsulin":0,"time":"2016-10-06T05:39:29.000Z"},{"iob":0,"activity":0,"bolussnooze":0,"basaliob":0,"netbasalinsulin":0,"hightempinsulin":0,"time":"2016-10-06T05:44:29.000Z"},{"iob":0,"activity":0,"bolussnooze":0,"basaliob":0,"netbasalinsulin":0,"hightempinsulin":0,"time":"2016-10-06T05:49:29.000Z"},{"iob":0,"activity":0,"bolussnooze":0,"basaliob":0,"netbasalinsulin":0,"hightempinsulin":0,"time":"2016-10-06T05:54:29.000Z"},{"iob":0,"activity":0,"bolussnooze":0,"basaliob":0,"netbasalinsulin":0,"hightempinsulin":0,"time":"2016-10-06T05:59:29.000Z"},{"iob":0,"activity":0,"bolussnooze":0,"basaliob":0,"netbasalinsulin":0,"hightempinsulin":0,"time":"2016-10-06T06:04:29.000Z"},{"iob":0,"activity":0,"bolussnooze":0,"basaliob":0,"netbasalinsulin":0,"hightempinsulin":0,"time":"2016-10-06T06:09:29.000Z"},{"iob":0,"activity":0,"bolussnooze":0,"basaliob":0,"netbasalinsulin":0,"hightempinsulin":0,"time":"2016-10-06T06:14:29.000Z"},{"iob":0,"activity":0,"bolussnooze":0,"basaliob":0,"netbasalinsulin":0,"hightempinsulin":0,"time":"2016-10-06T06:19:29.000Z"},{"iob":0,"activity":0,"bolussnooze":0,"basaliob":0,"netbasalinsulin":0,"hightempinsulin":0,"time":"2016-10-06T06:24:29.000Z"}]
