[{"iob":-0.553,"activity":-0.004,"bolussnooze":0,"basaliob":-0.553,"netbasalinsulin":-1.2,"hightempinsulin":0.25,"time":"2016-10-08T01:21:31.000Z"},{"iob":-0.582,"activity":-0.0043,"bolussnooze":0,"basaliob":-0.582,"netbasalinsulin":-1.2,"hightempinsulin":0.25,"time":"2016-10-08T01:26:31.000Z"},{"iob":-0.609,"activity":-0.0046,"bolussnooze":0,"basaliob":-0.609,"netbasalinsulin":-1.15,"hightempinsulin":0.25,"time":"2016-10-08T01:31:31.000Z"},{"iob":-0.634,"activity":-0.0049,"bolussnooze":0,"basaliob":-0.634,"netbasalinsulin":-1.15,"hightempinsulin":0.25,"time":"2016-10-08T01:36:31.000Z"},{"iob":-0.658,"activity":-0.0053,"bolussnooze":0,"basaliob":-0.658,"netbasalinsulin":-1.15,"hightempinsulin":0.25,"time":"2016-10-08T01:41:31.000Z"},{"iob":-0.63,"activity":-0.0056,"bolussnooze":0,"basaliob":-0.63,"netbasalinsulin":-1.1,"hightempinsulin":0.25,"time":"2016-10-08T01:46:31.000Z"},{"iob":-0.6,"activity":-0.0059,"bolussnooze":0,"basaliob":-0.6,"netbasalinsulin":-1,"hightempinsulin":0.25,"time":"2016-10-08T01:51:31.000Z"},{"iob":-0.569,"activity":-0.0061,"bolussnooze":0,"basaliob":-0.569,"netbasalinsulin":-0.95,"hightempinsulin":0.25,"time":"2016-10-08T01:56:31.000Z"},{"iob":-0.538,"activity":-0.0064,"bolussnooze":0,"basaliob":-0.538,"netbasalinsulin":-0.9,"hightempinsulin":0.25,"time":"2016-10-08T02:01:31.000Z"},{"iob":-0.505,"activity":-0.0066,"bolussnooze":0,"basaliob":-0.505,"netbasalinsulin":-0.85,"hightempinsulin":0.25,"time":"2016-10-08T02:06:31.000Z"},{"iob":-0.471,"activity":-0.0067,"bolussnooze":0,"basaliob":-0.471,"netbasalinsulin":-0.8,"hightempinsulin":0.25,"time":"2016-10-08T02:11:31.000Z"},{"iob":-0.437,"activity":-0.0068,"bolussnooze":0,"basaliob":-0.437,"netbasalinsulin":-0.75,"hightempinsulin":0.25,"time":"2016-10-08T02:16:31.000Z"},{"iob":-0.403,"activity":-0.0068,"bolussnooze":0,"basaliob":-0.403,"netbasalinsulin":-0.7,"hightempinsulin":0.25,"time":"2016-10-08T02:21:31.000Z"},{"iob":-0.369,"activity":-0.0069,"bolussnooze":0,"basaliob":-0.369,"netbasalinsulin":-0.65,"hightempinsulin":0.25,"time":"2016-10-08T02:26:31.000Z"},{"iob":-0.335,"activity":-0.0069,"bolussnooze":0,"basaliob":-0.335,"netbasalinsulin":-0.65,"hightempinsulin":0.25,"time":"2016-10-08T02:31:31.000Z"},{"iob":-0.301,"activity":-0.0068,"bolussnooze":0,"basaliob":-0.301,"netbasalinsulin":-0.65,"hightempinsulin":0.25,"time":"2016-10-08T02:36:31.000Z"},{"iob":-0.268,"activity":-0.0066,"bolussnooze":0,"basaliob":-0.268,"netbasalinsulin":-0.7,"hightempinsulin":0.2,"time":"2016-10-08T02:41:31.000Z"},{"iob":-0.236,"activity":-0.0063,"bolussnooze":0,"basaliob":-0.236,"netbasalinsulin":-0.8,"hightempinsulin":0.1,"time":"2016-10-08T02:46:31.000Z"},{"iob":-0.206,"activity":-0.006,"bolussnooze":0,"basaliob":-0.206,"netbasalinsulin":-0.85,"hightempinsulin":0.05,"time":"2016-10-08T02:51:31.000Z"},{"iob":-0.178,"activity":-0.0055,"bolussnooze":0,"basaliob":-0.178,"netbasalinsulin":-0.9,"hightempinsulin":0,"time":"2016-10-08T02:56:31.000Z"},{"iob":-0.153,"activity":-0.0051,"bolussnooze":0,"basaliob":-0.153,"netbasalinsulin":-0.9,"hightempinsulin":0,"time":"2016-10-08T03:01:31.000Z"},{"iob":-0.13,"activity":-0.0046,"bolussnooze":0,"basaliob":-0.13,"netbasalinsulin":-0.9,"hightempinsulin":0,"time":"2016-10-08T03:06:31.000Z"},{"iob":-0.11,"activity":-0.0041,"bolussnooze":0,"basaliob":-0.11,"netbasalinsulin":-0.9,"hightempinsulin":0,"time":"2016-10-08T03:11:31.000Z"},{"iob":-0.091,"activity":-0.0036,"bolussnooze":0,"basaliob":-0.091,"netbasalinsulin":-0.85,"hightempinsulin":0,"time":"2016-10-08T03:16:31.000Z"},{"iob":-0.075,"activity":-0.0032,"bolussnooze":0,"basaliob":-0.075,"netbasalinsulin":-0.8,"hightempinsulin":0,"time":"2016-10-08T03:21:31.000Z"},{"iob":-0.061,"activity":-0.0028,"bolussnooze":0,"basaliob":-0.061,"netbasalinsulin":-0.75,"hightempinsulin":0,"time":"2016-10-08T03:26:31.000Z"},{"iob":-0.049,"activity":-0.0024,"bolussnooze":0,"basaliob":-0.049,"netbasalinsulin":-0.7,"hightempinsulin":0,"time":"2016-10-08T03:31:31.000Z"},{"iob":-0.039,"activity":-0.0021,"bolussnooze":0,"basaliob":-0.039,"netbasalinsulin":-0.65,"hightempinsulin":0,"time":"2016-10-08T03:36:31.000Z"},{"iob":-0.03,"activity":-0.0018,"bolussnooze":0,"basaliob":-0.03,"netbasalinsulin":-0.6,"hightempinsulin":0,"time":"2016-10-08T03:41:31.000Z"},{"iob":-0.022,"activity":-0.0015,"bolussnooze":0,"basaliob":-0.022,"netbasalinsulin":-0.55,"hightempinsulin":0,"time":"2016-10-08T03:46:31.000Z"},{"iob":-0.016,"activity":-0.0012,"bolussnooze":0,"basaliob":-0.016,"netbasalinsulin":-0.5,"hightempinsulin":0,"time":"2016-10-08T03:51:31.000Z"},{"iob":-0.012,"activity":-0.001,"bolussnooze":0,"basaliob":-0.012,"netbasalinsulin":-0.4,"hightempinsulin":0,"time":"2016-10-08T03:56:31.000Z"},{"iob":-0.008,"activity":-0.0008,"bolussnooze":0,"basaliob":-0.008,"netbasalinsulin":-0.35,"hightempinsulin":0,"time":"2016-10-08T04:01:31.000Z"},{"iob":-0.005,"activity":-0.0006,"bolussnooze":0,"basaliob":-0.005,"netbasalinsulin":-0.3,"hightempinsulin":0,"time":"2016-10-08T04:06:31.000Z"},{"iob":-0.003,"activity":-0.0004,"bolussnooze":0,"basaliob":-0.003,"netbasalinsulin":-0.3,"hightempinsulin":0,"time":"2016-10-08T04:11:31.000Z"},{"iob":-0.001,"activity":-0.0003,"bolussnooze":0,"basaliob":-0.001,"netbasalinsulin":-0.25,"hightempinsulin":0,"time":"2016-10-08T04:16:31.000Z"},{"iob":-0.001,"activity":-0.0002,"bolussnooze":0,"basaliob":-0.001,"netbasalinsulin":-0.2,"hightempinsulin":0,"time":"2016-10-08T04:21:31.000Z"},{"iob":0,"activity":-0.0001,"bolussnooze":0,"basaliob":0,"netbasalinsulin":-0.15,"hightempinsulin":0,"time":"2016-10-08T04:26:31.000Z"},{"iob":0,"activity":0,"bolussnooze":0,"basaliob":0,"netbasalinsulin":-0.1,"hightempinsulin":0,"time":"2016-10-08T04:31:31.000Z"},{"iob":0,"activity":0,"bolussnooze":0,"basaliob":0,"netbasalinsulin":-0.05,"hightempinsulin":0,"time":"2016-10-08T04:36:31.000Z"},{"iob":0,"activity":0,"bolussnooze":0,"basaliob":0,"netbasalinsulin":0,"hightempinsulin":0,"time":"2016-10-08T04:41:31.000Z"},{"iob":0,"activity":0,"bolussnooze":0,"basaliob":0,"netbasalinsulin":0,"hightempinsulin":0,"time":"2016-10-08T04:46:31.000Z"}]
