[{"iob":3.257,"activity":0.0398,"bolussnooze":0.661,"basaliob":1.028,"netbasalinsulin":1.05,"hightempinsulin":1.25,"time":"2016-10-08T05:01:32.000Z"},{"iob":3.155,"activity":0.0405,"bolussnooze":0.574,"basaliob":1.1,"netbasalinsulin":1.15,"hightempinsulin":1.35,"time":"2016-10-08T05:06:32.000Z"},{"iob":3.048,"activity":0.0412,"bolussnooze":0.488,"basaliob":1.166,"netbasalinsulin":1.25,"hightempinsulin":1.45,"time":"2016-10-08T05:11:32.000Z"},{"iob":2.94,"activity":0.0415,"bolussnooze":0.403,"basaliob":1.227,"netbasalinsulin":1.35,"hightempinsulin":1.55,"time":"2016-10-08T05:16:32.000Z"},{"iob":2.835,"activity":0.0411,"bolussnooze":0.32,"basaliob":1.282,"netbasalinsulin":1.45,"hightempinsulin":1.65,"time":"2016-10-08T05:21:32.000Z"},{"iob":2.632,"activity":0.0405,"bolussnooze":0.253,"basaliob":1.233,"netbasalinsulin":1.45,"hightempinsulin":1.65,"time":"2016-10-08T05:26:32.000Z"},{"iob":2.433,"activity":0.0399,"bolussnooze":0.199,"basaliob":1.179,"netbasalinsulin":1.45,"hightempinsulin":1.65,"time":"2016-10-08T05:31:32.000Z"},{"iob":2.237,"activity":0.0391,"bolussnooze":0.152,"basaliob":1.121,"netbasalinsulin":1.45,"hightempinsulin":1.65,"time":"2016-10-08T05:36:32.000Z"},{"iob":2.046,"activity":0.0382,"bolussnooze":0.111,"basaliob":1.06,"netbasalinsulin":1.45,"hightempinsulin":1.65,"time":"2016-10-08T05:41:32.000Z"},{"iob":1.86,"activity":0.0372,"bolussnooze":0.077,"basaliob":0.997,"netbasalinsulin":1.45,"hightempinsulin":1.65,"time":"2016-10-08T05:46:32.000Z"},{"iob":1.68,"activity":0.036,"bolussnooze":0.049,"basaliob":0.933,"netbasalinsulin":1.45,"hightempinsulin":1.65,"time":"2016-10-08T05:51:32.000Z"},{"iob":1.506,"activity":0.0347,"bolussnooze":0.027,"basaliob":0.867,"netbasalinsulin":1.45,"hightempinsulin":1.65,"time":"2016-10-08T05:56:32.000Z"},{"iob":1.342,"activity":0.0328,"bolussnooze":0.012,"basaliob":0.8,"netbasalinsulin":1.45,"hightempinsulin":1.65,"time":"2016-10-08T06:01:32.000Z"},{"iob":1.189,"activity":0.0307,"bolussnooze":0.003,"basaliob":0.733,"netbasalinsulin":1.45,"hightempinsulin":1.65,"time":"2016-10-08T06:06:32.000Z"},{"iob":1.046,"activity":0.0286,"bolussnooze":0,"basaliob":0.667,"netbasalinsulin":1.45,"hightempinsulin":1.65,"time":"2016-10-08T06:11:32.000Z"},{"iob":0.914,"activity":0.0263,"bolussnooze":0,"basaliob":0.601,"netbasalinsulin":1.5,"hightempinsulin":1.65,"time":"2016-10-08T06:16:32.000Z"},{"iob":0.795,"activity":0.0238,"bolussnooze":0,"basaliob":0.537,"netbasalinsulin":1.55,"hightempinsulin":1.65,"time":"2016-10-08T06:21:32.000Z"},{"iob":0.689,"activity":0.0212,"bolussnooze":0,"basaliob":0.475,"netbasalinsulin":1.6,"hightempinsulin":1.65,"time":"2016-10-08T06:26:32.000Z"},{"iob":0.596,"activity":0.0188,"bolussnooze":0,"basaliob":0.417,"netbasalinsulin":1.65,"hightempinsulin":1.65,"time":"2016-10-08T06:31:32.000Z"},{"iob":0.51,"activity":0.0172,"bolussnooze":0,"basaliob":0.363,"netbasalinsulin":1.65,"hightempinsulin":1.65,"time":"2016-10-08T06:36:32.000Z"},{"iob":0.432,"activity":0.0155,"bolussnooze":0,"basaliob":0.314,"netbasalinsulin":1.65,"hightempinsulin":1.65,"time":"2016-10-08T06:41:32.000Z"},{"iob":0.363,"activity":0.0138,"bolussnooze":0,"basaliob":0.268,"netbasalinsulin":1.65,"hightempinsulin":1.65,"time":"2016-10-08T06:46:32.000Z"},{"iob":0.303,"activity":0.0122,"bolussnooze":0,"basaliob":0.227,"netbasalinsulin":1.65,"hightempinsulin":1.65,"time":"2016-10-08T06:51:32.000Z"},{"iob":0.25,"activity":0.0105,"bolussnooze":0,"basaliob":0.191,"netbasalinsulin":1.65,"hightempinsulin":1.65,"time":"2016-10-08T06:56:32.000Z"},{"iob":0.205,"activity":0.0091,"bolussnooze":0,"basaliob":0.159,"netbasalinsulin":1.5,"hightempinsulin":1.5,"time":"2016-10-08T07:01:32.000Z"},{"iob":0.165,"activity":0.008,"bolussnooze":0,"basaliob":0.13,"netbasalinsulin":1.45,"hightempinsulin":1.45,"time":"2016-10-08T07:06:32.000Z"},{"iob":0.131,"activity":0.0069,"bolussnooze":0,"basaliob":0.105,"netbasalinsulin":1.3,"hightempinsulin":1.3,"time":"2016-10-08T07:11:32.000Z"},{"iob":0.101,"activity":0.0059,"bolussnooze":0,"basaliob":0.084,"netbasalinsulin":1.25,"hightempinsulin":1.25,"time":"2016-10-08T07:16:32.000Z"},{"iob":0.076,"activity":0.005,"bolussnooze":0,"basaliob":0.066,"netbasalinsulin":1.15,"hightempinsulin":1.15,"time":"2016-10-08T07:21:32.000Z"},{"iob":0.056,"activity":0.0041,"bolussnooze":0,"basaliob":0.05,"netbasalinsulin":1,"hightempinsulin":1,"time":"2016-10-08T07:26:32.000Z"},{"iob":0.04,"activity":0.0033,"bolussnooze":0,"basaliob":0.037,"netbasalinsulin":0.95,"hightempinsulin":0.95,"time":"2016-10-08T07:31:32.000Z"},{"iob":0.027,"activity":0.0025,"bolussnooze":0,"basaliob":0.027,"netbasalinsulin":0.8,"hightempinsulin":0.8,"time":"2016-10-08T07:36:32.000Z"},{"iob":0.018,"activity":0.0017,"bolussnooze":0,"basaliob":0.019,"netbasalinsulin":0.75,"hightempinsulin":0.75,"time":"2016-10-08T07:41:32.000Z"},{"iob":0.012,"activity":0.0013,"bolussnooze":0,"basaliob":0.012,"netbasalinsulin":0.7,"hightempinsulin":0.7,"time":"2016-10-08T07:46:32.000Z"},{"iob":0.007,"activity":0.001,"bolussnooze":0,"basaliob":0.007,"netbasalinsulin":0.65,"hightempinsulin":0.65,"time":"2016-10-08T07:51:32.000Z"},{"iob":0.004,"activity":0.0007,"bolussnooze":0,"basaliob":0.004,"netbasalinsulin":0.5,"hightempinsulin":0.5,"time":"2016-10-08T07:56:32.000Z"},{"iob":0.002,"activity":0.0004,"bolussnooze":0,"basaliob":0.002,"netbasalinsulin":0.4,"hightempinsulin":0.4,"time":"2016-10-08T08:01:32.000Z"},{"iob":0.001,"activity":0.0002,"bolussnooze":0,"basaliob":0.001,"netbasalinsulin":0.3,"hightempinsulin":0.3,"time":"2016-10-08T08:06:32.000Z"},{"iob":0,"activity":0.0001,"bolussnooze":0,"basaliob":0,"netbasalinsulin":0.2,"hightempinsulin":0.2,"time":"2016-10-08T08:11:32.000Z"},{"iob":0,"activity":0,"bolussnooze":0,"basaliob":0,"netbasalinsulin":0.1,"hightempinsulin":0.1,"time":"2016-10-08T08:16:32.000Z"},{"iob":0,"activity":0,"bolussnooze":0,"basaliob":0,"netbasalinsulin":0,"hightempinsulin":0,"time":"2016-10-08T08:21:32.000Z"},{"iob":0,"activity":0,"bolussnooze":0,"basaliob":0,"netbasalinsulin":0,"hightempinsulin":0,"time":"2016-10-08T08:26:32.000Z"}]
