{
  "bg": 148, 
  "temp": "absolute", 
  "snoozeBG": 111, 
  "predBGs": {
    "IOB": [
      148, 
      149, 
      150, 
      151, 
      151, 
      150, 
      149, 
      147, 
      145, 
      142, 
      138, 
      134, 
      129, 
      124, 
      119, 
      114, 
      109, 
      105, 
      100, 
      96, 
      92, 
      88, 
      84, 
      81, 
      78, 
      75, 
      72, 
      70, 
      67, 
      65, 
      64, 
      62, 
      61, 
      60, 
      59, 
      59, 
      58
    ]
  }, 
  "rate": 1.15, 
  "reason": "COB: 0, Dev: 41, BGI: -4.9, ISF: 100, Target: 80; Eventual BG 111 >= 80, 24m@1.200 = 0.480 > req 0.31+20%. Setting temp basal of 1.15U/hr", 
  "COB": 0, 
  "eventualBG": 111, 
  "duration": 30, 
  "tick": "+2", 
  "IOB": 0.782
}