{
  "device": "openaps://indy-e1", 
  "pump": {
    "battery": {
      "status": "normal", 
      "voltage": 1.58
    }, 
    "status": {
      "status": "normal", 
      "timestamp": "2016-10-03T03:31:33.000Z", 
      "bolusing": false, 
      "suspended": false
    }, 
    "reservoir": 121.175, 
    "clock": "2016-10-02T20:31:41-07:00"
  }, 
  "uploader": {
    "battery": 100, 
    "batteryVoltage": 4370
  }, 
  "openaps": {
    "suggested": {
      "bg": 116, 
      "temp": "absolute", 
      "snoozeBG": 121, 
      "timestamp": "2016-10-03T03:33:13.000Z", 
      "reason": "COB: 25, Dev: 62, BGI: -10.34, ISF: 99, Target: 120; Eventual BG 169 >= 120, temp 0.675<0.7U/hr", 
      "rate": 0.7, 
      "COB": 25, 
      "eventualBG": 169, 
      "duration": 30, 
      "tick": "+1", 
      "IOB": 0.697
    }, 
    "iob": {
      "netbasalinsulin": -0.45, 
      "timestamp": "2016-10-03T03:31:41.000Z", 
      "activity": 0.0209, 
      "basaliob": -0.085, 
      "hightempinsulin": 0.55, 
      "bolussnooze": 0, 
      "iob": 0.697
    }, 
    "enacted": {
      "bg": 116, 
      "temp": "absolute", 
      "snoozeBG": 121, 
      "recieved": true, 
      "predBGs": {
        "COB": [
          116, 
          116, 
          115, 
          115, 
          115, 
          115, 
          116, 
          117, 
          119, 
          121, 
          123, 
          126, 
          128, 
          131, 
          135, 
          138, 
          142, 
          146, 
          150, 
          153, 
          156, 
          159, 
          162, 
          164, 
          166, 
          167, 
          168, 
          168, 
          169
        ], 
        "aCOB": [
          116, 
          115, 
          115, 
          114, 
          114, 
          114, 
          115, 
          116, 
          117, 
          119, 
          121, 
          124, 
          127, 
          130, 
          133, 
          136, 
          140, 
          144, 
          148, 
          152, 
          155, 
          158, 
          161, 
          163, 
          165, 
          167, 
          168, 
          168, 
          169
        ], 
        "IOB": [
          116, 
          115, 
          114, 
          112, 
          110, 
          108, 
          106, 
          104, 
          102, 
          100, 
          97, 
          95, 
          92, 
          89, 
          88, 
          87, 
          86, 
          86, 
          87, 
          87, 
          88, 
          89, 
          90, 
          90, 
          91, 
          92, 
          92, 
          93
        ]
      }, 
      "rate": 0.675, 
      "reason": "COB: 25, Dev: 62, BGI: -10.34, ISF: 99, Target: 120; Eventual BG 169 >= 120, temp 0.675<0.7U/hr", 
      "COB": 25, 
      "eventualBG": 169, 
      "timestamp": "2016-10-03T03:33:34.000Z", 
      "duration": 30, 
      "tick": "+1", 
      "IOB": 0.697
    }
  }, 
  "mmtune": {
    "scanDetails": [
      [
        "916.564", 
        5, 
        -73
      ], 
      [
        "916.588", 
        5, 
        -58
      ], 
      [
        "916.612", 
        5, 
        -55
      ], 
      [
        "916.636", 
        5, 
        -56
      ], 
      [
        "916.660", 
        5, 
        -55
      ], 
      [
        "916.684", 
        5, 
        -57
      ], 
      [
        "916.708", 
        5, 
        -67
      ]
    ], 
    "setFreq": 916.66, 
    "timestamp": "2016-10-03T03:31:12.000Z", 
    "usedDefault": false
  }
}