{
  "device": "openaps://indy-e1", 
  "pump": {
    "battery": {
      "status": "normal", 
      "voltage": 1.56
    }, 
    "status": {
      "status": "normal", 
      "timestamp": "2016-10-08T05:27:28.000Z", 
      "bolusing": false, 
      "suspended": false
    }, 
    "reservoir": 139.1, 
    "clock": "2016-10-07T22:27:38-07:00"
  }, 
  "uploader": {
    "battery": 56, 
    "batteryVoltage": 3740
  }, 
  "openaps": {
    "suggested": {
      "bg": 305, 
      "temp": "absolute", 
      "snoozeBG": 312, 
      "timestamp": "2016-10-08T05:29:05.000Z", 
      "reason": "COB: 37, Dev: 141, BGI: -19.5, ISF: 100, Target: 80; Eventual BG 269 >= 80, adj. req. rate: 4.55 to maxSafeBasal: 3.25, temp 0<3.25U/hr", 
      "rate": 3.25, 
      "COB": 37, 
      "eventualBG": 269, 
      "duration": 30, 
      "tick": "+4", 
      "IOB": 2.155
    }, 
    "iob": {
      "netbasalinsulin": 0.7, 
      "timestamp": "2016-10-08T05:27:38.000Z", 
      "activity": 0.039, 
      "basaliob": 0.489, 
      "hightempinsulin": 1.25, 
      "bolussnooze": 0.538, 
      "iob": 2.155
    }, 
    "enacted": {
      "bg": 305, 
      "temp": "absolute", 
      "snoozeBG": 312, 
      "recieved": true, 
      "predBGs": {
        "COB": [
          305, 
          308, 
          310, 
          311, 
          311, 
          311, 
          310, 
          309, 
          307, 
          306, 
          304, 
          303, 
          301, 
          299, 
          298, 
          295, 
          292, 
          288, 
          284, 
          281, 
          278, 
          276, 
          274, 
          272, 
          271, 
          270, 
          270, 
          269
        ], 
        "aCOB": [
          305, 
          295, 
          286, 
          277, 
          268, 
          260, 
          252, 
          245, 
          239, 
          234, 
          230, 
          227, 
          225, 
          224, 
          224, 
          224, 
          225, 
          226, 
          228, 
          230, 
          233, 
          235, 
          238, 
          241, 
          244, 
          247, 
          250, 
          253, 
          256, 
          259, 
          262, 
          265, 
          267, 
          269, 
          270, 
          272, 
          273, 
          274, 
          275, 
          275, 
          276
        ], 
        "IOB": [
          305, 
          307, 
          308, 
          307, 
          305, 
          302, 
          297, 
          291, 
          285, 
          278, 
          270, 
          262, 
          253, 
          245, 
          239, 
          233, 
          228, 
          223, 
          219, 
          216, 
          213, 
          211, 
          209, 
          208, 
          206, 
          206, 
          205, 
          205, 
          205, 
          204
        ]
      }, 
      "rate": 3.25, 
      "reason": "COB: 37, Dev: 141, BGI: -19.5, ISF: 100, Target: 80; Eventual BG 269 >= 80, adj. req. rate: 4.55 to maxSafeBasal: 3.25, temp 0<3.25U/hr", 
      "COB": 37, 
      "eventualBG": 269, 
      "timestamp": "2016-10-08T05:29:25.000Z", 
      "duration": 30, 
      "tick": "+4", 
      "IOB": 2.155
    }
  }, 
  "mmtune": {
    "scanDetails": [
      [
        "916.540", 
        5, 
        -57
      ], 
      [
        "916.564", 
        5, 
        -53
      ], 
      [
        "916.588", 
        5, 
        -52
      ], 
      [
        "916.612", 
        5, 
        -53
      ], 
      [
        "916.636", 
        5, 
        -53
      ], 
      [
        "916.660", 
        5, 
        -50
      ], 
      [
        "916.684", 
        5, 
        -65
      ]
    ], 
    "setFreq": 916.66, 
    "timestamp": "2016-10-08T05:27:07.000Z", 
    "usedDefault": false
  }
}