{
  "device": "openaps://indy-e1", 
  "pump": {
    "battery": {
      "status": "normal", 
      "voltage": 1.56
    }, 
    "status": {
      "status": "normal", 
      "timestamp": "2016-10-03T23:06:26.000Z", 
      "bolusing": false, 
      "suspended": false
    }, 
    "reservoir": 104.25, 
    "clock": "2016-10-03T16:06:35-07:00"
  }, 
  "uploader": {
    "battery": 54, 
    "batteryVoltage": 3717
  }, 
  "openaps": {
    "suggested": {
      "bg": 80, 
      "temp": "absolute", 
      "snoozeBG": 98, 
      "timestamp": "2016-10-03T23:08:17.000Z", 
      "reason": "COB: 20, Dev: -18, BGI: -2.14, ISF: 91, Target: 116; BG 80<83", 
      "rate": 0, 
      "COB": 20, 
      "eventualBG": 21, 
      "duration": 30, 
      "tick": -5, 
      "IOB": 0.446
    }, 
    "iob": {
      "netbasalinsulin": 0.3, 
      "timestamp": "2016-10-03T23:06:35.000Z", 
      "activity": 0.0047, 
      "basaliob": -0.29, 
      "hightempinsulin": 0.75, 
      "bolussnooze": 0.565, 
      "iob": 0.446
    }, 
    "enacted": {
      "bg": 80, 
      "temp": "absolute", 
      "snoozeBG": 98, 
      "recieved": true, 
      "predBGs": {
        "aCOB": [
          80, 
          85, 
          89, 
          93, 
          97, 
          101, 
          105, 
          108, 
          112, 
          114, 
          117, 
          119, 
          122, 
          124, 
          125, 
          127, 
          128, 
          129, 
          130, 
          130, 
          129, 
          129, 
          129, 
          129, 
          128, 
          128, 
          128, 
          128, 
          128, 
          129, 
          129, 
          129, 
          129, 
          130
        ], 
        "IOB": [
          80, 
          75, 
          71, 
          66, 
          62, 
          59, 
          55, 
          52, 
          49, 
          47, 
          44, 
          42, 
          40, 
          39
        ]
      }, 
      "rate": 0, 
      "reason": "COB: 20, Dev: -18, BGI: -2.14, ISF: 91, Target: 116; BG 80<83", 
      "COB": 20, 
      "eventualBG": 21, 
      "timestamp": "2016-10-03T23:08:37.000Z", 
      "duration": 30, 
      "tick": -5, 
      "IOB": 0.446
    }
  }, 
  "mmtune": {
    "scanDetails": [
      [
        "916.564", 
        5, 
        -74
      ], 
      [
        "916.588", 
        5, 
        -70
      ], 
      [
        "916.612", 
        5, 
        -68
      ], 
      [
        "916.636", 
        5, 
        -69
      ], 
      [
        "916.660", 
        5, 
        -78
      ], 
      [
        "916.684", 
        5, 
        -75
      ], 
      [
        "916.708", 
        4, 
        -86
      ]
    ], 
    "setFreq": 916.612, 
    "timestamp": "2016-10-03T23:06:05.000Z", 
    "usedDefault": false
  }
}