{
  "device": "openaps://indy-e1", 
  "pump": {
    "battery": {
      "status": "normal", 
      "voltage": 1.43
    }, 
    "status": {
      "status": "normal", 
      "timestamp": "2016-10-06T07:04:01.000Z", 
      "bolusing": false, 
      "suspended": false
    }, 
    "reservoir": 106.875, 
    "clock": "2016-10-06T00:04:09-07:00"
  }, 
  "uploader": {
    "battery": 100, 
    "batteryVoltage": 4360
  }, 
  "openaps": {
    "suggested": {
      "bg": 172, 
      "temp": "absolute", 
      "snoozeBG": 123, 
      "timestamp": "2016-10-06T07:06:00.000Z", 
      "predBGs": {
        "IOB": [
          172, 
          168, 
          164, 
          160, 
          156, 
          152, 
          148, 
          145, 
          142, 
          139, 
          136, 
          134, 
          131, 
          129, 
          128, 
          126, 
          125, 
          124, 
          124, 
          123, 
          123, 
          122, 
          122, 
          122, 
          122, 
          123, 
          123, 
          123, 
          123, 
          123, 
          123, 
          123, 
          124
        ]
      }, 
      "reason": "COB: 0, Dev: 2, BGI: -4.36, ISF: 90, Target: 115; Eventual BG 123 >= 115, temp 0.675<0.775U/hr, but 30m left and 0.675 ~ req 0.775U/hr: no action required", 
      "COB": 0, 
      "eventualBG": 123, 
      "tick": -4, 
      "IOB": 0.564
    }, 
    "iob": {
      "netbasalinsulin": 1.05, 
      "timestamp": "2016-10-06T07:04:09.000Z", 
      "activity": 0.0097, 
      "basaliob": 0.564, 
      "hightempinsulin": 1.25, 
      "bolussnooze": 0, 
      "iob": 0.564
    }, 
    "enacted": {
      "bg": 179, 
      "temp": "absolute", 
      "snoozeBG": 127, 
      "recieved": true, 
      "rate": 0.975, 
      "reason": "COB: 0, Dev: 10, BGI: -4, ISF: 90, Target: 115; Eventual BG 127 >= 115, temp 0.5<0.975U/hr", 
      "COB": 0, 
      "eventualBG": 127, 
      "timestamp": "2016-10-06T06:53:26.000Z", 
      "duration": 30, 
      "tick": "+1", 
      "IOB": 0.686
    }
  }, 
  "mmtune": {
    "scanDetails": [
      [
        "916.540", 
        5, 
        -83
      ], 
      [
        "916.564", 
        5, 
        -72
      ], 
      [
        "916.588", 
        5, 
        -71
      ], 
      [
        "916.612", 
        5, 
        -70
      ], 
      [
        "916.636", 
        5, 
        -70
      ], 
      [
        "916.660", 
        5, 
        -71
      ], 
      [
        "916.684", 
        5, 
        -75
      ]
    ], 
    "setFreq": 916.636, 
    "timestamp": "2016-10-06T07:03:36.000Z", 
    "usedDefault": false
  }
}